kipoi_veff/__init__.py
kipoi_veff/__main__.py
kipoi_veff/cli.py
kipoi_veff/logging.conf
kipoi_veff/mutation_map.py
kipoi_veff/parsers.py
kipoi_veff/scores.py
kipoi_veff/snv_predict.py
kipoi_veff/specs.py
kipoi_veff/external/__init__.py
kipoi_veff/external/concise/__init__.py
kipoi_veff/external/concise/seqplotting_deps.py
kipoi_veff/external/concise/seqplotting_letters.py
kipoi_veff/utils/__init__.py
kipoi_veff/utils/dna_reshapers.py
kipoi_veff/utils/generic.py
kipoi_veff/utils/io.py
kipoi_veff/utils/mutators.py
kipoi_veff/utils/plot.py
kipoi_veff/utils/scoring_fns.py
kipoi_veff-0.3.1.dist-info/LICENSE
kipoi_veff-0.3.1.dist-info/METADATA
kipoi_veff-0.3.1.dist-info/WHEEL
kipoi_veff-0.3.1.dist-info/top_level.txt
kipoi_veff-0.3.1.dist-info/RECORD
